{
	"AWSTemplateFormatVersion" : "2010-09-09",
	"Description": "This AWS CloudFormation template searches for an image by name. **WARNING** This template creates one AWS Lambda function and calls it. You will be billed for the AWS resources used if you create a stack from this template.",
	"Parameters": {
		"AMIName" : {
			"Description": "Base name of the AMI ID to find",
			"Type"       : "String",
			"MinLength"  : "1"
		}
	},
	"Resources" : {
		"FindImageRole": {
			"Type": "AWS::IAM::Role",
			"Properties": {
				"AssumeRolePolicyDocument": {
					"Version": "2012-10-17",
					"Statement": [
						{
							"Sid": "",
							"Effect": "Allow",
							"Principal": {
								"Service": "lambda.amazonaws.com"
							},
							"Action": "sts:AssumeRole"
						}
					]
				},
				"Path": "/",
				"Policies": [
					{
						"PolicyName": "root",
						"PolicyDocument": {
							"Version": "2012-10-17",
							"Statement": [
								{
									"Effect": "Allow",
									"Action": [
										"logs:CreateLogGroup",
										"logs:CreateLogStream",
										"logs:PutLogEvents",
										"ec2:DescribeImages"
									],
									"Resource": "*"
								}
							]
						}
					}
				]
			}
		},
		"FindImageFunction": {
			"Type" : "AWS::Lambda::Function",
			"Properties" : {
				"Code" : {
					"S3Bucket" : "<BUCKETNAME>",
					"S3Key" : "<PREFIX>lambda/find-image.zip"
				},
				"Description" : "AWS Lambda function for searching images based on name",
				"Handler" : "find-image.handler",
				"MemorySize" : "128",
				"Role" : { "Fn::GetAtt" : [ "FindImageRole", "Arn" ] },
				"Runtime" : "nodejs10.x",
				"Timeout" : "25"
			}
		},
		"FindImage" : {
			"Type" : "Custom::FindImage",
			"Properties" : {
				"ServiceToken": { "Fn::GetAtt" : [ "FindImageFunction", "Arn" ] },
				"ImageName": { "Ref": "AMIName" }
			}
	    }
	},
	"Outputs": {
		"AMIId": {
			"Description": "Identified of the specified image",
			"Value" : { "Fn::GetAtt" : [ "FindImage", "ImageId" ] }
		}
	}
}
